{
  "$type": "Bespoke.Sph.Domain.EntityForm, domain.sph",
  "FormDesign": {
    "$type": "Bespoke.Sph.Domain.FormDesign, domain.sph",
    "FormElementCollection": {
      "$type": "Bespoke.Sph.Domain.ObjectCollection`1[[Bespoke.Sph.Domain.FormElement, domain.sph]], domain.sph",
      "$values": [
        {
          "$type": "Bespoke.Sph.Domain.TextBox, domain.sph",
          "DefaultValue": null,
          "AutoCompletionEntity": null,
          "AutoCompletionField": null,
          "AutoCompletionQuery": null,
          "IsPathIsRequired": true,
          "TypeName": "TextBox",
          "FieldValidation": {
            "$type": "Bespoke.Sph.Domain.FieldValidation, domain.sph",
            "IsRequired": false,
            "Pattern": null,
            "Mode": "",
            "Message": null,
            "Min": null,
            "Max": null,
            "MinLength": null,
            "MaxLength": null,
            "WebId": null
          },
          "Name": null,
          "Label": "No",
          "Tooltip": null,
          "Path": "No",
          "IsRequired": false,
          "Size": "input-large",
          "CssClass": "",
          "Visible": "true",
          "Enable": "true",
          "ElementId": "18da7668-aabe-4ff1-8b01-5ed7a5b66e49",
          "HelpText": null,
          "UseDisplayTemplate": false,
          "ToolboxIconClass": null,
          "IsUniqueName": false,
          "LabelColLg": null,
          "LabelColMd": null,
          "LabelColSm": null,
          "LabelColXs": null,
          "InputColLg": null,
          "InputColMd": null,
          "InputColSm": null,
          "InputColXs": null,
          "WebId": "02465b19-2322-4bdb-f9b4-d9cfbd97d30e"
        },
        {
          "$type": "Bespoke.Sph.Domain.TextBox, domain.sph",
          "DefaultValue": null,
          "AutoCompletionEntity": null,
          "AutoCompletionField": null,
          "AutoCompletionQuery": null,
          "IsPathIsRequired": true,
          "TypeName": "TextBox",
          "FieldValidation": {
            "$type": "Bespoke.Sph.Domain.FieldValidation, domain.sph",
            "IsRequired": false,
            "Pattern": null,
            "Mode": "",
            "Message": null,
            "Min": null,
            "Max": null,
            "MinLength": null,
            "MaxLength": null,
            "WebId": null
          },
          "Name": null,
          "Label": "Bahagian",
          "Tooltip": null,
          "Path": "Bahagian",
          "IsRequired": false,
          "Size": "input-large",
          "CssClass": "",
          "Visible": "true",
          "Enable": "true",
          "ElementId": "c888907e-12f5-4649-b376-b3b1e853f307",
          "HelpText": null,
          "UseDisplayTemplate": false,
          "ToolboxIconClass": null,
          "IsUniqueName": false,
          "LabelColLg": null,
          "LabelColMd": null,
          "LabelColSm": null,
          "LabelColXs": null,
          "InputColLg": null,
          "InputColMd": null,
          "InputColSm": null,
          "InputColXs": null,
          "WebId": "d7fdba1d-b1ed-4c5b-a80a-a5310820e89e"
        },
        {
          "$type": "Bespoke.Sph.Domain.ComboBox, domain.sph",
          "ComboBoxItemCollection": {
            "$type": "Bespoke.Sph.Domain.ObjectCollection`1[[Bespoke.Sph.Domain.ComboBoxItem, domain.sph]], domain.sph",
            "$values": [
              {
                "$type": "Bespoke.Sph.Domain.ComboBoxItem, domain.sph",
                "Caption": "Minda",
                "Value": "Minda",
                "WebId": "6932fe83-85cd-47f5-f175-a39aeb911609"
              },
              {
                "$type": "Bespoke.Sph.Domain.ComboBoxItem, domain.sph",
                "Caption": "Emosi",
                "Value": "Emosi",
                "WebId": "5ea2986b-ba08-4ca5-90bb-87a03f8bd4ae"
              },
              {
                "$type": "Bespoke.Sph.Domain.ComboBoxItem, domain.sph",
                "Caption": "Spiritual",
                "Value": "Spiritual",
                "WebId": "56319c8f-b87c-47b7-9398-9b2b72fdb58a"
              },
              {
                "$type": "Bespoke.Sph.Domain.ComboBoxItem, domain.sph",
                "Caption": "Sosial",
                "Value": "Sosial",
                "WebId": "ea20acbb-5e20-4e58-f886-fdb809f59337"
              },
              {
                "$type": "Bespoke.Sph.Domain.ComboBoxItem, domain.sph",
                "Caption": "Fizikal",
                "Value": "Fizikal",
                "WebId": "73ba3e5d-70b1-4d08-92f5-ce6150341b8b"
              },
              {
                "$type": "Bespoke.Sph.Domain.ComboBoxItem, domain.sph",
                "Caption": "Kewangan",
                "Value": "Kewangan",
                "WebId": "770bc942-1ffd-44c9-b417-538be1eddd74"
              },
              {
                "$type": "Bespoke.Sph.Domain.ComboBoxItem, domain.sph",
                "Caption": "Persekitaran",
                "Value": "Persekitaran",
                "WebId": "2b25d8b7-d896-4736-aff4-cfde007b0ca6"
              },
              {
                "$type": "Bespoke.Sph.Domain.ComboBoxItem, domain.sph",
                "Caption": "Pekerjaan",
                "Value": "Pekerjaan",
                "WebId": "340a1c57-0d76-4878-f42f-7218b0c585b7"
              }
            ]
          },
          "ComboBoxLookup": {
            "$type": "Bespoke.Sph.Domain.ComboBoxLookup, domain.sph",
            "Entity": null,
            "ValuePath": null,
            "DisplayPath": null,
            "Query": null,
            "IsComputedQuery": false,
            "WebId": null
          },
          "IsPathIsRequired": true,
          "TypeName": "ComboBox",
          "FieldValidation": {
            "$type": "Bespoke.Sph.Domain.FieldValidation, domain.sph",
            "IsRequired": false,
            "Pattern": null,
            "Mode": "",
            "Message": null,
            "Min": null,
            "Max": null,
            "MinLength": null,
            "MaxLength": null,
            "WebId": null
          },
          "Name": null,
          "Label": "Tret",
          "Tooltip": null,
          "Path": "Tret",
          "IsRequired": false,
          "Size": "input-large",
          "CssClass": "",
          "Visible": "true",
          "Enable": "true",
          "ElementId": "400d8212-5903-4305-ef69-794ff008f34c",
          "HelpText": null,
          "UseDisplayTemplate": false,
          "ToolboxIconClass": null,
          "IsUniqueName": false,
          "LabelColLg": null,
          "LabelColMd": null,
          "LabelColSm": null,
          "LabelColXs": null,
          "InputColLg": null,
          "InputColMd": null,
          "InputColSm": null,
          "InputColXs": null,
          "WebId": "7c0ab1cd-e166-49b1-efc4-737a35ff5ef7"
        },
        {
          "$type": "Bespoke.Sph.Domain.ComboBox, domain.sph",
          "ComboBoxItemCollection": {
            "$type": "Bespoke.Sph.Domain.ObjectCollection`1[[Bespoke.Sph.Domain.ComboBoxItem, domain.sph]], domain.sph",
            "$values": [
              {
                "$type": "Bespoke.Sph.Domain.ComboBoxItem, domain.sph",
                "Caption": "Tinggi",
                "Value": "Tinggi",
                "WebId": "1989d43a-7efd-4656-94a3-3d5211341554"
              },
              {
                "$type": "Bespoke.Sph.Domain.ComboBoxItem, domain.sph",
                "Caption": "Rendah",
                "Value": "Rendah",
                "WebId": "958b7314-b445-4e19-9bf6-36db3994371c"
              }
            ]
          },
          "ComboBoxLookup": {
            "$type": "Bespoke.Sph.Domain.ComboBoxLookup, domain.sph",
            "Entity": null,
            "ValuePath": null,
            "DisplayPath": null,
            "Query": null,
            "IsComputedQuery": false,
            "WebId": null
          },
          "IsPathIsRequired": true,
          "TypeName": "ComboBox",
          "FieldValidation": {
            "$type": "Bespoke.Sph.Domain.FieldValidation, domain.sph",
            "IsRequired": false,
            "Pattern": null,
            "Mode": "",
            "Message": null,
            "Min": null,
            "Max": null,
            "MinLength": null,
            "MaxLength": null,
            "WebId": null
          },
          "Name": null,
          "Label": "Tahap",
          "Tooltip": null,
          "Path": "Tahap",
          "IsRequired": false,
          "Size": "input-large",
          "CssClass": "",
          "Visible": "true",
          "Enable": "true",
          "ElementId": "1956be64-65df-47ce-bc86-c1c3b0d72331",
          "HelpText": null,
          "UseDisplayTemplate": false,
          "ToolboxIconClass": null,
          "IsUniqueName": false,
          "LabelColLg": null,
          "LabelColMd": null,
          "LabelColSm": null,
          "LabelColXs": null,
          "InputColLg": null,
          "InputColMd": null,
          "InputColSm": null,
          "InputColXs": null,
          "WebId": "9a5ba437-5ce5-4c8a-8d2e-c09ead72d6ca"
        },
        {
          "$type": "Bespoke.Sph.Domain.TextBox, domain.sph",
          "DefaultValue": null,
          "AutoCompletionEntity": null,
          "AutoCompletionField": null,
          "AutoCompletionQuery": null,
          "IsPathIsRequired": true,
          "TypeName": "TextBox",
          "FieldValidation": {
            "$type": "Bespoke.Sph.Domain.FieldValidation, domain.sph",
            "IsRequired": false,
            "Pattern": null,
            "Mode": "",
            "Message": null,
            "Min": null,
            "Max": null,
            "MinLength": null,
            "MaxLength": null,
            "WebId": null
          },
          "Name": null,
          "Label": "Nilai Min",
          "Tooltip": null,
          "Path": "NilaiMin",
          "IsRequired": false,
          "Size": "input-large",
          "CssClass": "",
          "Visible": "true",
          "Enable": "true",
          "ElementId": "d1827890-f59c-469c-9dbf-6e51cd3fbc0b",
          "HelpText": null,
          "UseDisplayTemplate": false,
          "ToolboxIconClass": null,
          "IsUniqueName": false,
          "LabelColLg": null,
          "LabelColMd": null,
          "LabelColSm": null,
          "LabelColXs": null,
          "InputColLg": null,
          "InputColMd": null,
          "InputColSm": null,
          "InputColXs": null,
          "WebId": "31d5a794-fea5-4b60-9158-6e7dfab260be"
        },
        {
          "$type": "Bespoke.Sph.Domain.TextBox, domain.sph",
          "DefaultValue": null,
          "AutoCompletionEntity": null,
          "AutoCompletionField": null,
          "AutoCompletionQuery": null,
          "IsPathIsRequired": true,
          "TypeName": "TextBox",
          "FieldValidation": {
            "$type": "Bespoke.Sph.Domain.FieldValidation, domain.sph",
            "IsRequired": false,
            "Pattern": null,
            "Mode": "",
            "Message": null,
            "Min": null,
            "Max": null,
            "MinLength": null,
            "MaxLength": null,
            "WebId": null
          },
          "Name": null,
          "Label": "Nilai Max",
          "Tooltip": null,
          "Path": "NilaiMax",
          "IsRequired": false,
          "Size": "input-large",
          "CssClass": "",
          "Visible": "true",
          "Enable": "true",
          "ElementId": "65bf660c-441a-49e6-80c1-e772938f824f",
          "HelpText": null,
          "UseDisplayTemplate": false,
          "ToolboxIconClass": null,
          "IsUniqueName": false,
          "LabelColLg": null,
          "LabelColMd": null,
          "LabelColSm": null,
          "LabelColXs": null,
          "InputColLg": null,
          "InputColMd": null,
          "InputColSm": null,
          "InputColXs": null,
          "WebId": "284c6cc4-7f00-4162-ae3d-7be93cf565b9"
        },
        {
          "$type": "Bespoke.Sph.Domain.TextBox, domain.sph",
          "DefaultValue": null,
          "AutoCompletionEntity": null,
          "AutoCompletionField": null,
          "AutoCompletionQuery": null,
          "IsPathIsRequired": true,
          "TypeName": "TextBox",
          "FieldValidation": {
            "$type": "Bespoke.Sph.Domain.FieldValidation, domain.sph",
            "IsRequired": false,
            "Pattern": null,
            "Mode": "",
            "Message": null,
            "Min": null,
            "Max": null,
            "MinLength": null,
            "MaxLength": null,
            "WebId": null
          },
          "Name": null,
          "Label": "Interpretasi",
          "Tooltip": null,
          "Path": "Interpretasi",
          "IsRequired": false,
          "Size": "input-large",
          "CssClass": "",
          "Visible": "true",
          "Enable": "true",
          "ElementId": "3d0ed070-3a5e-44a6-bc20-be757ad785aa",
          "HelpText": null,
          "UseDisplayTemplate": false,
          "ToolboxIconClass": null,
          "IsUniqueName": false,
          "LabelColLg": null,
          "LabelColMd": null,
          "LabelColSm": null,
          "LabelColXs": null,
          "InputColLg": null,
          "InputColMd": null,
          "InputColSm": null,
          "InputColXs": null,
          "WebId": "ef5a32dd-59ec-4de0-e420-adea95508cf6"
        }
      ]
    },
    "Name": null,
    "Description": null,
    "ConfirmationText": null,
    "ImageStoreId": null,
    "LabelColLg": null,
    "LabelColMd": null,
    "LabelColSm": null,
    "LabelColXs": null,
    "InputColLg": null,
    "InputColMd": null,
    "InputColSm": null,
    "InputColXs": null,
    "WebId": null
  },
  "Rules": {
    "$type": "Bespoke.Sph.Domain.ObjectCollection`1[[System.String, mscorlib]], domain.sph",
    "$values": []
  },
  "RouteParameterCollection": {
    "$type": "Bespoke.Sph.Domain.ObjectCollection`1[[Bespoke.Sph.Domain.RouteParameter, domain.sph]], domain.sph",
    "$values": []
  },
  "FormLayoutCollection": {
    "$type": "Bespoke.Sph.Domain.ObjectCollection`1[[Bespoke.Sph.Domain.FormLayout, domain.sph]], domain.sph",
    "$values": []
  },
  "EntityDefinitionId": "i2krecommendation",
  "Name": "I2kRecommendation details",
  "Route": "i2krecommendation-details",
  "Note": null,
  "IsAllowedNewItem": true,
  "IconClass": null,
  "IconStoreId": null,
  "IsPublished": true,
  "IsDefault": true,
  "IsWatchAvailable": false,
  "IsEmailAvailable": false,
  "IsPrintAvailable": false,
  "IsAuditTrailAvailable": false,
  "IsRemoveAvailable": true,
  "IsImportAvailable": false,
  "IsExportAvailable": false,
  "Operation": "save",
  "Entity": "I2kRecommendation",
  "Partial": "partial/i2krecommendation-details",
  "Caption": null,
  "Layout": " ",
  "CreatedBy": "admin",
  "Id": "57855320-6800-44af-8330-b8fb26920323",
  "CreatedDate": "2015-10-21T10:48:36.8378643+08:00",
  "ChangedBy": "admin",
  "ChangedDate": "2015-10-21T11:19:14.7778643+08:00",
  "WebId": "dc78ab41-27c0-4b46-bf0a-dfcc858ea43b"
}