{
  "$type": "Bespoke.epsikologi_jabatan.Domain.Jabatan, epsikologi.Jabatan",
  "JabatanNo": "jabatan-mufti-negeri-perlis",
  "NamaJabatan": "JABATAN MUFTI NEGERI PERLIS",
  "AgensiNo": "NA",
  "Kementerian": "PENTADBIRAN KERAJAAN NEGERI PERLIS",
  "AgensiKumpulan": "PAN",
  "CreatedBy": "erymuzuan",
  "Id": "jabatan-mufti-negeri-perlis",
  "CreatedDate": "2015-08-07T19:18:51.1740209+08:00",
  "ChangedBy": "admin",
  "ChangedDate": "2015-08-07T19:18:51.1740209+08:00",
  "WebId": "42bd3a14-a5c3-4450-8be4-b0cfc45500db"
}