{
  "$type": "Bespoke.epsikologi_jabatan.Domain.Jabatan, epsikologi.Jabatan",
  "JabatanNo": "jabatan-pembangunan-sumber-manusia",
  "NamaJabatan": "JABATAN PEMBANGUNAN SUMBER MANUSIA",
  "AgensiNo": "NA",
  "Kementerian": "PENTADBIRAN KERAJAAN NEGERI SABAH",
  "AgensiKumpulan": "PAN",
  "CreatedBy": "erymuzuan",
  "Id": "jabatan-pembangunan-sumber-manusia",
  "CreatedDate": "2015-08-07T19:18:51.1745205+08:00",
  "ChangedBy": "admin",
  "ChangedDate": "2015-08-07T19:18:51.1745205+08:00",
  "WebId": "e6985718-62c5-4a00-a97e-4c9b41dc6de6"
}