{
  "$type": "Bespoke.epsikologi_jabatan.Domain.Jabatan, epsikologi.Jabatan",
  "JabatanNo": "jabatan-cetak-kerajaan",
  "NamaJabatan": "JABATAN CETAK KERAJAAN",
  "AgensiNo": "NA",
  "Kementerian": "PENTADBIRAN KERAJAAN NEGERI SABAH",
  "AgensiKumpulan": "PAN",
  "CreatedBy": "erymuzuan",
  "Id": "jabatan-cetak-kerajaan",
  "CreatedDate": "2015-08-07T19:18:51.1745205+08:00",
  "ChangedBy": "admin",
  "ChangedDate": "2015-08-07T19:18:51.1745205+08:00",
  "WebId": "6bd11070-7a41-49bf-b716-728b931ab184"
}