{
  "$type": "Bespoke.epsikologi_jabatan.Domain.Jabatan, epsikologi.Jabatan",
  "JabatanNo": "lembaga-pertubuhan-peladang",
  "NamaJabatan": "LEMBAGA PERTUBUHAN PELADANG",
  "AgensiNo": "NA",
  "Kementerian": "KEMENTERIAN PERTANIAN DAN INDUSTRI ASAS TANI",
  "AgensiKumpulan": "BBP",
  "CreatedBy": "erymuzuan",
  "Id": "lembaga-pertubuhan-peladang",
  "CreatedDate": "2015-08-08T07:27:15.5889253+08:00",
  "ChangedBy": "admin",
  "ChangedDate": "2015-08-08T07:27:15.5889253+08:00",
  "WebId": "de717837-af3d-4515-8632-14c1fa66e72b"
}