{
  "$type": "Bespoke.epsikologi_jabatan.Domain.Jabatan, epsikologi.Jabatan",
  "JabatanNo": "majlis-peperiksaan-malaysia",
  "NamaJabatan": "MAJLIS PEPERIKSAAN MALAYSIA",
  "AgensiNo": "NA",
  "Kementerian": "KEMENTERIAN PENDIDIKAN MALAYSIA",
  "AgensiKumpulan": "BBP",
  "CreatedBy": "erymuzuan",
  "Id": "majlis-peperiksaan-malaysia",
  "CreatedDate": "2015-08-08T07:27:15.5884271+08:00",
  "ChangedBy": "admin",
  "ChangedDate": "2015-08-08T07:27:15.5884271+08:00",
  "WebId": "66ea2b7f-0c63-4cc9-a4d5-335db5c4ba00"
}