{
  "$type": "Bespoke.epsikologi_jabatan.Domain.Jabatan, epsikologi.Jabatan",
  "JabatanNo": "pentadbiran-kerajaan-negeri-sarawak",
  "NamaJabatan": "PENTADBIRAN KERAJAAN NEGERI SARAWAK",
  "AgensiNo": "NA",
  "Kementerian": "PENTADBIRAN KERAJAAN NEGERI SARAWAK",
  "AgensiKumpulan": "PAN",
  "CreatedBy": "erymuzuan",
  "Id": "pentadbiran-kerajaan-negeri-sarawak",
  "CreatedDate": "2015-08-07T19:18:51.1745205+08:00",
  "ChangedBy": "admin",
  "ChangedDate": "2015-08-07T19:18:51.1745205+08:00",
  "WebId": "6ce54613-10fd-4a5a-b9c6-4ad4790b5204"
}