{
  "$type": "Bespoke.epsikologi_jabatan.Domain.Jabatan, epsikologi.Jabatan",
  "JabatanNo": "perbadanan-stadium-negeri-sarawak",
  "NamaJabatan": "PERBADANAN STADIUM NEGERI SARAWAK",
  "AgensiNo": "NA",
  "Kementerian": "PENTADBIRAN KERAJAAN NEGERI SARAWAK",
  "AgensiKumpulan": "BBN",
  "CreatedBy": "erymuzuan",
  "Id": "perbadanan-stadium-negeri-sarawak",
  "CreatedDate": "2015-08-07T19:18:51.1750204+08:00",
  "ChangedBy": "admin",
  "ChangedDate": "2015-08-07T19:18:51.1750204+08:00",
  "WebId": "91abcb0b-3a25-4da4-8cb1-b6a28d73475d"
}