{
  "$type": "Bespoke.epsikologi_jabatan.Domain.Jabatan, epsikologi.Jabatan",
  "JabatanNo": "universiti-sains-malaysia-usm-",
  "NamaJabatan": "UNIVERSITI SAINS MALAYSIA (USM)",
  "AgensiNo": "NA",
  "Kementerian": "KEMENTERIAN PENDIDIKAN MALAYSIA",
  "AgensiKumpulan": "BBP",
  "CreatedBy": "erymuzuan",
  "Id": "universiti-sains-malaysia-usm-",
  "CreatedDate": "2015-08-08T07:27:15.5884271+08:00",
  "ChangedBy": "admin",
  "ChangedDate": "2015-08-08T07:27:15.5884271+08:00",
  "WebId": "eaba1a4b-74ae-4cd2-94ad-7352ad37d915"
}