{
  "$type": "Bespoke.epsikologi_jabatan.Domain.Jabatan, epsikologi.Jabatan",
  "JabatanNo": "yayasan-islam-terengganu",
  "NamaJabatan": "YAYASAN ISLAM TERENGGANU",
  "AgensiNo": "NA",
  "Kementerian": "PENTADBIRAN KERAJAAN NEGERI TERENGGANU",
  "AgensiKumpulan": "BBN",
  "CreatedBy": "erymuzuan",
  "Id": "yayasan-islam-terengganu",
  "CreatedDate": "2015-08-07T19:18:51.1755203+08:00",
  "ChangedBy": "admin",
  "ChangedDate": "2015-08-07T19:18:51.1755203+08:00",
  "WebId": "2c98329d-505d-4631-ac16-a1a3b58e6f09"
}