{
  "$type": "Bespoke.epsikologi_ipupercentilenorms.Domain.IpuPercentileNorms, epsikologi.IpuPercentileNorms",
  "No": "l-11",
  "RawScore": 11,
  "Jantina": "Lelaki",
  "A": 57,
  "B": 75,
  "C": 5,
  "D": 3,
  "E": 2,
  "F": 64,
  "G": 5,
  "H": 62,
  "I": 5,
  "CreatedBy": "urusetia1",
  "Id": "d94dc464-e71d-4de2-8034-a2ab7828f938",
  "CreatedDate": "2015-08-03T12:55:09.5628095+08:00",
  "ChangedBy": "urusetia1",
  "ChangedDate": "2015-08-03T12:55:09.5608093+08:00",
  "WebId": "43c39ca7-f673-4621-dae1-dd808d6db3b3"
}