{
  "$type": "Bespoke.epsikologi_soalan.Domain.Soalan, epsikologi.Soalan",
  "NoRujukan": "HLP-00014",
  "SoalanNo": "HLP-00014",
  "TeksSoalan": "Saya berasa kehidupan ini tidak bermakna dan mengecewakan.,,,",
  "SeksyenSoalan": null,
  "PilihanJawapanCollection": {
    "$type": "Bespoke.Sph.Domain.ObjectCollection`1[[Bespoke.epsikologi_soalan.Domain.PilihanJawapan, epsikologi.Soalan]], domain.sph",
    "$values": [
      {
        "$type": "Bespoke.epsikologi_soalan.Domain.PilihanJawapan, epsikologi.Soalan",
        "Teks": "Ya",
        "Nilai": 2,
        "WebId": null
      },
      {
        "$type": "Bespoke.epsikologi_soalan.Domain.PilihanJawapan, epsikologi.Soalan",
        "Teks": "Tidak",
        "Nilai": 0,
        "WebId": null
      }
    ]
  },
  "Trait": "KC",
  "NamaUjian": "Ujian Khas Hadiah Latihan Persekutuan(HLP)",
  "Susunan": 14.0,
  "Kategori": "Keceriaan",
  "CreatedBy": "admin",
  "Id": "HLP-00014",
  "CreatedDate": "2015-07-06T11:24:49.383606+08:00",
  "ChangedBy": "admin",
  "ChangedDate": "2015-07-07T16:24:01.7351161+08:00",
  "WebId": "255e8860-fb28-4833-85cb-346ec775794e"
}