{
  "$type": "Bespoke.epsikologi_soalan.Domain.Soalan, epsikologi.Soalan",
  "NoRujukan": "HLP-00083",
  "SoalanNo": "HLP-00083",
  "TeksSoalan": "Saya kerap memendam perasaan sehingga ke tahap ?menunggu masa untuk meletup.?,,,",
  "SeksyenSoalan": null,
  "PilihanJawapanCollection": {
    "$type": "Bespoke.Sph.Domain.ObjectCollection`1[[Bespoke.epsikologi_soalan.Domain.PilihanJawapan, epsikologi.Soalan]], domain.sph",
    "$values": [
      {
        "$type": "Bespoke.epsikologi_soalan.Domain.PilihanJawapan, epsikologi.Soalan",
        "Teks": "Ya",
        "Nilai": 2,
        "WebId": null
      },
      {
        "$type": "Bespoke.epsikologi_soalan.Domain.PilihanJawapan, epsikologi.Soalan",
        "Teks": "Tidak",
        "Nilai": 0,
        "WebId": null
      }
    ]
  },
  "Trait": "KT",
  "NamaUjian": "HLP",
  "Susunan": 83.0,
  "Kategori": "Ketenangan",
  "Bahagian": null,
  "CreatedBy": "admin",
  "Id": "HLP-00083",
  "CreatedDate": "2015-07-06T11:24:49.8494345+08:00",
  "ChangedBy": "admin",
  "ChangedDate": "2015-07-08T08:22:34.1600049+08:00",
  "WebId": "4538e9f3-e337-4144-aef4-fdaad25a4ce2"
}