{
  "$type": "Bespoke.epsikologi_soalan.Domain.Soalan, epsikologi.Soalan",
  "NoRujukan": "0603",
  "SoalanNo": "0603",
  "TeksSoalan": "Ahli Muzik.",
  "SeksyenSoalan": "3",
  "PilihanJawapanCollection": {
    "$type": "Bespoke.Sph.Domain.ObjectCollection`1[[Bespoke.epsikologi_soalan.Domain.PilihanJawapan, epsikologi.Soalan]], domain.sph",
    "$values": [
      {
        "$type": "Bespoke.epsikologi_soalan.Domain.PilihanJawapan, epsikologi.Soalan",
        "Teks": "Ya",
        "Nilai": 1,
        "WebId": null
      },
      {
        "$type": "Bespoke.epsikologi_soalan.Domain.PilihanJawapan, epsikologi.Soalan",
        "Teks": "Tidak",
        "Nilai": 0,
        "WebId": null
      }
    ]
  },
  "Trait": "C3",
  "NamaUjian": "IBK",
  "Susunan": 1.0,
  "Kategori": "Kreatif",
  "Bahagian": null,
  "CreatedBy": "admin",
  "Id": "IBK-3-0603",
  "CreatedDate": "2015-07-06T11:24:45.0600541+08:00",
  "ChangedBy": "Urusetia01",
  "ChangedDate": "2015-08-05T14:24:06.0317551+08:00",
  "WebId": "410ddf9a-9101-42c6-92fc-dd7d8c57997b"
}