{
  "$type": "Bespoke.epsikologi_soalan.Domain.Soalan, epsikologi.Soalan",
  "NoRujukan": "0696",
  "SoalanNo": "0696",
  "TeksSoalan": "Menghadiri persidangan perniagaan.",
  "SeksyenSoalan": "1",
  "PilihanJawapanCollection": {
    "$type": "Bespoke.Sph.Domain.ObjectCollection`1[[Bespoke.epsikologi_soalan.Domain.PilihanJawapan, epsikologi.Soalan]], domain.sph",
    "$values": [
      {
        "$type": "Bespoke.epsikologi_soalan.Domain.PilihanJawapan, epsikologi.Soalan",
        "Teks": "Ya",
        "Nilai": 1,
        "WebId": "acd3795f-cccb-4b89-8159-234626a87154"
      },
      {
        "$type": "Bespoke.epsikologi_soalan.Domain.PilihanJawapan, epsikologi.Soalan",
        "Teks": "Tidak",
        "Nilai": 0,
        "WebId": "78b34717-451a-465f-ba4d-d0fdb6937c1e"
      }
    ]
  },
  "Trait": "E1",
  "NamaUjian": "IBK",
  "Susunan": 47.0,
  "Kategori": "Inovatif",
  "Bahagian": null,
  "CreatedBy": "admin",
  "Id": "IBK-1-0696",
  "CreatedDate": "2015-07-06T11:24:49.0773903+08:00",
  "ChangedBy": "admin",
  "ChangedDate": "2015-08-26T11:58:08.1139744+08:00",
  "WebId": "104098f6-fc03-4eef-966d-9455f6941569"
}