{
  "$type": "Bespoke.epsikologi_soalan.Domain.Soalan, epsikologi.Soalan",
  "NoRujukan": "0587",
  "SoalanNo": "0587",
  "TeksSoalan": "Juruterbang Helikopter.",
  "SeksyenSoalan": "3",
  "PilihanJawapanCollection": {
    "$type": "Bespoke.Sph.Domain.ObjectCollection`1[[Bespoke.epsikologi_soalan.Domain.PilihanJawapan, epsikologi.Soalan]], domain.sph",
    "$values": [
      {
        "$type": "Bespoke.epsikologi_soalan.Domain.PilihanJawapan, epsikologi.Soalan",
        "Teks": "Ya",
        "Nilai": 1,
        "WebId": null
      },
      {
        "$type": "Bespoke.epsikologi_soalan.Domain.PilihanJawapan, epsikologi.Soalan",
        "Teks": "Tidak",
        "Nilai": 0,
        "WebId": null
      }
    ]
  },
  "Trait": "A3",
  "NamaUjian": "IBK",
  "Susunan": 1.0,
  "Kategori": "Praktikal",
  "Bahagian": null,
  "CreatedBy": "admin",
  "Id": "IBK-3-0587",
  "CreatedDate": "2015-07-06T11:24:44.8348956+08:00",
  "ChangedBy": "Urusetia01",
  "ChangedDate": "2015-08-05T14:14:20.6242202+08:00",
  "WebId": "d1158cb7-21e6-4b73-8076-287124cb3b6b"
}