{
  "$type": "Bespoke.epsikologi_soalan.Domain.Soalan, epsikologi.Soalan",
  "NoRujukan": "0989",
  "SoalanNo": "0989",
  "TeksSoalan": "Hati saya mudah tersentuh apabila membaca berita yang mendukacitakan.",
  "SeksyenSoalan": "",
  "PilihanJawapanCollection": {
    "$type": "Bespoke.Sph.Domain.ObjectCollection`1[[Bespoke.epsikologi_soalan.Domain.PilihanJawapan, epsikologi.Soalan]], domain.sph",
    "$values": []
  },
  "Trait": "NA",
  "NamaUjian": "IPE",
  "Susunan": 1.0,
  "Kategori": null,
  "Bahagian": null,
  "CreatedBy": "admin",
  "Id": "IPE--0989",
  "CreatedDate": "2015-07-06T11:24:47.9395868+08:00",
  "ChangedBy": "admin",
  "ChangedDate": "2015-07-06T11:24:47.9385861+08:00",
  "WebId": "9658d8d2-adb5-4926-8340-3716eb3f875d"
}