{
  "$type": "Bespoke.epsikologi_soalan.Domain.Soalan, epsikologi.Soalan",
  "NoRujukan": "0970",
  "SoalanNo": "0970",
  "TeksSoalan": "Saya tidak kisah apabila diminta bekerja lebih masa.",
  "SeksyenSoalan": "",
  "PilihanJawapanCollection": {
    "$type": "Bespoke.Sph.Domain.ObjectCollection`1[[Bespoke.epsikologi_soalan.Domain.PilihanJawapan, epsikologi.Soalan]], domain.sph",
    "$values": []
  },
  "Trait": "NA",
  "NamaUjian": "IPE",
  "Susunan": 1.0,
  "Kategori": null,
  "Bahagian": null,
  "CreatedBy": "admin",
  "Id": "IPE--0970",
  "CreatedDate": "2015-07-06T11:24:47.8139979+08:00",
  "ChangedBy": "admin",
  "ChangedDate": "2015-07-06T11:24:47.8134973+08:00",
  "WebId": "33d24261-1f3b-4a73-8544-59f361bc7e85"
}