{
  "$type": "Bespoke.epsikologi_soalan.Domain.Soalan, epsikologi.Soalan",
  "NoRujukan": "0259",
  "SoalanNo": "0259",
  "TeksSoalan": "Saya lebih suka membaca atau menonton televisyen selepas waktu kerja daripada keluar atau melibatkan diri dalam kegiatan sosial.",
  "SeksyenSoalan": "",
  "PilihanJawapanCollection": {
    "$type": "Bespoke.Sph.Domain.ObjectCollection`1[[Bespoke.epsikologi_soalan.Domain.PilihanJawapan, epsikologi.Soalan]], domain.sph",
    "$values": [
      {
        "$type": "Bespoke.epsikologi_soalan.Domain.PilihanJawapan, epsikologi.Soalan",
        "Teks": "Ya",
        "Nilai": 0,
        "WebId": null
      },
      {
        "$type": "Bespoke.epsikologi_soalan.Domain.PilihanJawapan, epsikologi.Soalan",
        "Teks": "Tidak",
        "Nilai": 2,
        "WebId": null
      }
    ]
  },
  "Trait": "C",
  "NamaUjian": "Indikator Perwatakan Unggul (IPU)",
  "Susunan": 149.0,
  "Kategori": null,
  "Bahagian": null,
  "CreatedBy": "admin",
  "Id": "IPU-C-0259",
  "CreatedDate": "2015-07-06T11:24:42.2050389+08:00",
  "ChangedBy": "Urusetia01",
  "ChangedDate": "2015-08-05T15:22:06.3147486+08:00",
  "WebId": "a41730fd-c52d-4b18-b6ad-ff815a1293f6"
}