{
  "$type": "Bespoke.epsikologi_soalan.Domain.Soalan, epsikologi.Soalan",
  "NoRujukan": "0720",
  "SoalanNo": "0720",
  "TeksSoalan": "Saya meluangkan masa untuk bergembira.",
  "SeksyenSoalan": "",
  "PilihanJawapanCollection": {
    "$type": "Bespoke.Sph.Domain.ObjectCollection`1[[Bespoke.epsikologi_soalan.Domain.PilihanJawapan, epsikologi.Soalan]], domain.sph",
    "$values": [
      {
        "$type": "Bespoke.epsikologi_soalan.Domain.PilihanJawapan, epsikologi.Soalan",
        "Teks": "Ya",
        "Nilai": 1,
        "WebId": null
      },
      {
        "$type": "Bespoke.epsikologi_soalan.Domain.PilihanJawapan, epsikologi.Soalan",
        "Teks": "Tidak",
        "Nilai": 0,
        "WebId": null
      }
    ]
  },
  "Trait": "NA",
  "NamaUjian": "Inventori Stres Organisasi (ISO)",
  "Susunan": 1.0,
  "Kategori": null,
  "CreatedBy": "admin",
  "Id": "ISO--0720",
  "CreatedDate": "2015-07-06T11:24:46.1032911+08:00",
  "ChangedBy": "admin",
  "ChangedDate": "2015-07-06T11:24:46.1027901+08:00",
  "WebId": "5ac6c100-d641-4149-96a2-c4c85b77d8d1"
}