{
  "$type": "Bespoke.epsikologi_soalan.Domain.Soalan, epsikologi.Soalan",
  "NoRujukan": "0663",
  "SoalanNo": "0663",
  "TeksSoalan": "Saya kurang jelas dengan objektif kerja.",
  "SeksyenSoalan": "",
  "PilihanJawapanCollection": {
    "$type": "Bespoke.Sph.Domain.ObjectCollection`1[[Bespoke.epsikologi_soalan.Domain.PilihanJawapan, epsikologi.Soalan]], domain.sph",
    "$values": [
      {
        "$type": "Bespoke.epsikologi_soalan.Domain.PilihanJawapan, epsikologi.Soalan",
        "Teks": "Ya",
        "Nilai": 1,
        "WebId": null
      },
      {
        "$type": "Bespoke.epsikologi_soalan.Domain.PilihanJawapan, epsikologi.Soalan",
        "Teks": "Tidak",
        "Nilai": 0,
        "WebId": null
      }
    ]
  },
  "Trait": "B",
  "NamaUjian": "Inventori Stres Organisasi (ISO)",
  "Susunan": 14.0,
  "Kategori": "Ukuran Stres Kerja",
  "Bahagian": null,
  "CreatedBy": "admin",
  "Id": "ISO--0663",
  "CreatedDate": "2015-06-22T16:26:34.337191+08:00",
  "ChangedBy": "Urusetia02",
  "ChangedDate": "2015-08-05T10:06:40.8723748+08:00",
  "WebId": "748ea95c-b704-47dc-ac52-82b73166bade"
}