{
  "$type": "Bespoke.epsikologi_soalan.Domain.Soalan, epsikologi.Soalan",
  "NoRujukan": "UKBP-A-00144",
  "SoalanNo": "UKBP-A-00144",
  "TeksSoalan": "Saya mempunyai pelbagai minat.",
  "SeksyenSoalan": "",
  "PilihanJawapanCollection": {
    "$type": "Bespoke.Sph.Domain.ObjectCollection`1[[Bespoke.epsikologi_soalan.Domain.PilihanJawapan, epsikologi.Soalan]], domain.sph",
    "$values": [
      {
        "$type": "Bespoke.epsikologi_soalan.Domain.PilihanJawapan, epsikologi.Soalan",
        "Teks": "Ya",
        "Nilai": 2,
        "WebId": null
      },
      {
        "$type": "Bespoke.epsikologi_soalan.Domain.PilihanJawapan, epsikologi.Soalan",
        "Teks": "Tidak",
        "Nilai": 0,
        "WebId": null
      }
    ]
  },
  "Trait": "AKS",
  "NamaUjian": "UKBP-A",
  "Susunan": 144.0,
  "Kategori": null,
  "Bahagian": "A",
  "CreatedBy": "admin",
  "Id": "UKBP-A-00144",
  "CreatedDate": "2015-07-06T11:24:54.9145099+08:00",
  "ChangedBy": "admin",
  "ChangedDate": "2015-07-07T16:22:04.2269353+08:00",
  "WebId": "30bd837e-cfd6-4053-af72-dafde478bf5d"
}