{
  "$type": "Bespoke.epsikologi_soalan.Domain.Soalan, epsikologi.Soalan",
  "NoRujukan": "UKBP-A-00060",
  "SoalanNo": "UKBP-A-00060",
  "TeksSoalan": "Pada hari ini saya berasa tidak mudah berputus asa terhadap sesuatu perkara.",
  "SeksyenSoalan": "",
  "PilihanJawapanCollection": {
    "$type": "Bespoke.Sph.Domain.ObjectCollection`1[[Bespoke.epsikologi_soalan.Domain.PilihanJawapan, epsikologi.Soalan]], domain.sph",
    "$values": [
      {
        "$type": "Bespoke.epsikologi_soalan.Domain.PilihanJawapan, epsikologi.Soalan",
        "Teks": "Ya",
        "Nilai": 1,
        "WebId": null
      },
      {
        "$type": "Bespoke.epsikologi_soalan.Domain.PilihanJawapan, epsikologi.Soalan",
        "Teks": "Tidak",
        "Nilai": 0,
        "WebId": null
      }
    ]
  },
  "Trait": "PTL2",
  "NamaUjian": "Ujian Khas Biasiswa Persekutuan(UKBP)",
  "Susunan": 60.0,
  "Kategori": null,
  "Bahagian": "A",
  "CreatedBy": "admin",
  "Id": "UKBP-A-00060",
  "CreatedDate": "2015-07-06T11:24:54.1799909+08:00",
  "ChangedBy": "admin",
  "ChangedDate": "2015-07-07T14:24:07.2375117+08:00",
  "WebId": "623f7ffc-f488-4591-b77d-634e3046f7a3"
}